LICENSE.md
esg_matching/__init__.py
esg_matching/data_source/__init__.py
esg_matching/data_source/db_match.py
esg_matching/data_source/db_source.py
esg_matching/engine/__init__.py
esg_matching/engine/builders/__init__.py
esg_matching/engine/builders/sql_builder.py
esg_matching/engine/builders/table_builder.py
esg_matching/engine/connectors/__init__.py
esg_matching/engine/connectors/base_connector.py
esg_matching/engine/connectors/oracle.py
esg_matching/engine/connectors/sql_lite.py
esg_matching/engine/connectors/trino.py
esg_matching/engine/sql/__init__.py
esg_matching/engine/sql/dml.py
esg_matching/engine/sql/dql.py
esg_matching/exceptions/__init__.py
esg_matching/exceptions/exceptions_builders.py
esg_matching/exceptions/exceptions_data_source.py
esg_matching/exceptions/exceptions_db_engine.py
esg_matching/exceptions/exceptions_file.py
esg_matching/exceptions/exceptions_matching_policy.py
esg_matching/exceptions/exceptions_settings.py
esg_matching/file_reader/__init__.py
esg_matching/file_reader/base_reader.py
esg_matching/file_reader/csv_reader.py
esg_matching/file_reader/file.py
esg_matching/file_reader/settings.py
esg_matching/file_reader/utils.py
esg_matching/matcher/__init__.py
esg_matching/matcher/db_matcher.py
esg_matching/matcher/dfm.py
esg_matching/matcher/drm.py
esg_matching/matcher/irm.py
esg_matching/matcher/policy.py
esg_matching/processing/__init__.py
esg_matching/processing/etl.py
esg_matching/report/__init__.py
esg_matching/report/report_manager.py
esg_matching/report/report_matching.py
esg_matching-0.2.0.dist-info/entry_points.txt
esg_matching-0.2.0.dist-info/LICENSE.md
esg_matching-0.2.0.dist-info/WHEEL
esg_matching-0.2.0.dist-info/METADATA
esg_matching-0.2.0.dist-info/RECORD
