Metadata-Version: 2.1
Name: esg-matching
Version: 0.2.0
Summary: Entity matching of several data sources
Home-page: https://github.com/os-climate/esg-matching
License: Apache 2
Keywords: entity matching,matching,esg matching
Author: Os-Climate Foundation
Author-email: test_os-climate@gmail.com
Requires-Python: >=3.8,<3.11
Classifier: Development Status :: 5 - Production/Stable
Classifier: Intended Audience :: Developers
Classifier: License :: OSI Approved :: Apache Software License
Classifier: License :: Other/Proprietary License
Classifier: Operating System :: MacOS
Classifier: Operating System :: Microsoft :: Windows
Classifier: Operating System :: POSIX :: Linux
Classifier: Programming Language :: Python :: 3
Classifier: Programming Language :: Python :: 3.10
Classifier: Programming Language :: Python :: 3.7
Classifier: Programming Language :: Python :: 3.8
Classifier: Programming Language :: Python :: 3.9
Requires-Dist: SQLAlchemy (>=1.4.21)
Requires-Dist: cx_Oracle (>=8.3.0)
Requires-Dist: pandas (>=1.4.0)
Requires-Dist: sqlalchemy-trino (>=0.4.1)
Project-URL: Repository, https://github.com/os-climate/esg-matching
